<?xml version="1.0" encoding="utf-8"?>
<Data>
	<Node>
		<Id>1</Id>
		<Quality>0</Quality>
		<BagLabel>特殊</BagLabel>
		<MaxOwn>0</MaxOwn>
		<CanSell>不可出售</CanSell>
		<SellPrice>0</SellPrice>
		<CanUse>不可使用</CanUse>
		<CanUseBatch>0</CanUseBatch>
		<UseEffect>0</UseEffect>
		<UseEffectArgs>0</UseEffectArgs>
		<CompoundNumber>0</CompoundNumber>
		<CompoundHero>0</CompoundHero>
		<DayUseLimit>0</DayUseLimit>
	</Node>
	<Node>
		<Id>2</Id>
		<Quality>0</Quality>
		<BagLabel>特殊</BagLabel>
		<MaxOwn>0</MaxOwn>
		<CanSell>不可出售</CanSell>
		<SellPrice>0</SellPrice>
		<CanUse>不可使用</CanUse>
		<CanUseBatch>0</CanUseBatch>
		<UseEffect>0</UseEffect>
		<UseEffectArgs>0</UseEffectArgs>
		<CompoundNumber>0</CompoundNumber>
		<CompoundHero>0</CompoundHero>
		<DayUseLimit>0</DayUseLimit>
	</Node>
	<Node>
		<Id>3</Id>
		<Quality>0</Quality>
		<BagLabel>特殊</BagLabel>
		<MaxOwn>0</MaxOwn>
		<CanSell>不可出售</CanSell>
		<SellPrice>0</SellPrice>
		<CanUse>不可使用</CanUse>
		<CanUseBatch>0</CanUseBatch>
		<UseEffect>0</UseEffect>
		<UseEffectArgs>0</UseEffectArgs>
		<CompoundNumber>0</CompoundNumber>
		<CompoundHero>0</CompoundHero>
		<DayUseLimit>0</DayUseLimit>
	</Node>
	<Node>
		<Id>4</Id>
		<Quality>0</Quality>
		<BagLabel>特殊</BagLabel>
		<MaxOwn>0</MaxOwn>
		<CanSell>不可出售</CanSell>
		<SellPrice>0</SellPrice>
		<CanUse>不可使用</CanUse>
		<CanUseBatch>0</CanUseBatch>
		<UseEffect>0</UseEffect>
		<UseEffectArgs>0</UseEffectArgs>
		<CompoundNumber>0</CompoundNumber>
		<CompoundHero>0</CompoundHero>
		<DayUseLimit>0</DayUseLimit>
	</Node>
	<Node>
		<Id>5</Id>
		<Quality>0</Quality>
		<BagLabel>特殊</BagLabel>
		<MaxOwn>0</MaxOwn>
		<CanSell>不可出售</CanSell>
		<SellPrice>0</SellPrice>
		<CanUse>不可使用</CanUse>
		<CanUseBatch>0</CanUseBatch>
		<UseEffect>0</UseEffect>
		<UseEffectArgs>0</UseEffectArgs>
		<CompoundNumber>0</CompoundNumber>
		<CompoundHero>0</CompoundHero>
		<DayUseLimit>0</DayUseLimit>
	</Node>
	<Node>
		<Id>6</Id>
		<Quality>0</Quality>
		<BagLabel>特殊</BagLabel>
		<MaxOwn>0</MaxOwn>
		<CanSell>不可出售</CanSell>
		<SellPrice>0</SellPrice>
		<CanUse>不可使用</CanUse>
		<CanUseBatch>0</CanUseBatch>
		<UseEffect>0</UseEffect>
		<UseEffectArgs>0</UseEffectArgs>
		<CompoundNumber>0</CompoundNumber>
		<CompoundHero>0</CompoundHero>
		<DayUseLimit>0</DayUseLimit>
	</Node>
	<Node>
		<Id>11</Id>
		<Quality>0</Quality>
		<BagLabel>特殊</BagLabel>
		<MaxOwn>0</MaxOwn>
		<CanSell>不可出售</CanSell>
		<SellPrice>0</SellPrice>
		<CanUse>不可使用</CanUse>
		<CanUseBatch>0</CanUseBatch>
		<UseEffect>0</UseEffect>
		<UseEffectArgs>0</UseEffectArgs>
		<CompoundNumber>0</CompoundNumber>
		<CompoundHero>0</CompoundHero>
		<DayUseLimit>0</DayUseLimit>
	</Node>
	<Node>
		<Id>210101</Id>
		<Quality>绿</Quality>
		<BagLabel>道具</BagLabel>
		<MaxOwn>0</MaxOwn>
		<CanSell>不可出售</CanSell>
		<SellPrice>0</SellPrice>
		<CanUse>可以使用</CanUse>
		<CanUseBatch>1</CanUseBatch>
		<UseEffect>0</UseEffect>
		<UseEffectArgs>0</UseEffectArgs>
		<CompoundNumber>0</CompoundNumber>
		<CompoundHero>0</CompoundHero>
		<DayUseLimit>0</DayUseLimit>
	</Node>
	<Node>
		<Id>210102</Id>
		<Quality>蓝</Quality>
		<BagLabel>道具</BagLabel>
		<MaxOwn>0</MaxOwn>
		<CanSell>不可出售</CanSell>
		<SellPrice>0</SellPrice>
		<CanUse>可以使用</CanUse>
		<CanUseBatch>1</CanUseBatch>
		<UseEffect>0</UseEffect>
		<UseEffectArgs>0</UseEffectArgs>
		<CompoundNumber>0</CompoundNumber>
		<CompoundHero>0</CompoundHero>
		<DayUseLimit>0</DayUseLimit>
	</Node>
	<Node>
		<Id>210103</Id>
		<Quality>紫</Quality>
		<BagLabel>道具</BagLabel>
		<MaxOwn>0</MaxOwn>
		<CanSell>不可出售</CanSell>
		<SellPrice>0</SellPrice>
		<CanUse>可以使用</CanUse>
		<CanUseBatch>1</CanUseBatch>
		<UseEffect>0</UseEffect>
		<UseEffectArgs>0</UseEffectArgs>
		<CompoundNumber>0</CompoundNumber>
		<CompoundHero>0</CompoundHero>
		<DayUseLimit>0</DayUseLimit>
	</Node>
	<Node>
		<Id>210201</Id>
		<Quality>绿</Quality>
		<BagLabel>道具</BagLabel>
		<MaxOwn>0</MaxOwn>
		<CanSell>不可出售</CanSell>
		<SellPrice>0</SellPrice>
		<CanUse>可以使用</CanUse>
		<CanUseBatch>1</CanUseBatch>
		<UseEffect>0</UseEffect>
		<UseEffectArgs>0</UseEffectArgs>
		<CompoundNumber>0</CompoundNumber>
		<CompoundHero>0</CompoundHero>
		<DayUseLimit>0</DayUseLimit>
	</Node>
	<Node>
		<Id>210202</Id>
		<Quality>蓝</Quality>
		<BagLabel>道具</BagLabel>
		<MaxOwn>0</MaxOwn>
		<CanSell>不可出售</CanSell>
		<SellPrice>0</SellPrice>
		<CanUse>可以使用</CanUse>
		<CanUseBatch>1</CanUseBatch>
		<UseEffect>0</UseEffect>
		<UseEffectArgs>0</UseEffectArgs>
		<CompoundNumber>0</CompoundNumber>
		<CompoundHero>0</CompoundHero>
		<DayUseLimit>0</DayUseLimit>
	</Node>
	<Node>
		<Id>210203</Id>
		<Quality>紫</Quality>
		<BagLabel>道具</BagLabel>
		<MaxOwn>0</MaxOwn>
		<CanSell>不可出售</CanSell>
		<SellPrice>0</SellPrice>
		<CanUse>可以使用</CanUse>
		<CanUseBatch>1</CanUseBatch>
		<UseEffect>0</UseEffect>
		<UseEffectArgs>0</UseEffectArgs>
		<CompoundNumber>0</CompoundNumber>
		<CompoundHero>0</CompoundHero>
		<DayUseLimit>0</DayUseLimit>
	</Node>
	<Node>
		<Id>210301</Id>
		<Quality>绿</Quality>
		<BagLabel>道具</BagLabel>
		<MaxOwn>0</MaxOwn>
		<CanSell>不可出售</CanSell>
		<SellPrice>0</SellPrice>
		<CanUse>可以使用</CanUse>
		<CanUseBatch>0</CanUseBatch>
		<UseEffect>0</UseEffect>
		<UseEffectArgs>0</UseEffectArgs>
		<CompoundNumber>0</CompoundNumber>
		<CompoundHero>0</CompoundHero>
		<DayUseLimit>0</DayUseLimit>
	</Node>
	<Node>
		<Id>210302</Id>
		<Quality>蓝</Quality>
		<BagLabel>道具</BagLabel>
		<MaxOwn>0</MaxOwn>
		<CanSell>不可出售</CanSell>
		<SellPrice>0</SellPrice>
		<CanUse>可以使用</CanUse>
		<CanUseBatch>0</CanUseBatch>
		<UseEffect>0</UseEffect>
		<UseEffectArgs>0</UseEffectArgs>
		<CompoundNumber>0</CompoundNumber>
		<CompoundHero>0</CompoundHero>
		<DayUseLimit>0</DayUseLimit>
	</Node>
	<Node>
		<Id>210303</Id>
		<Quality>紫</Quality>
		<BagLabel>道具</BagLabel>
		<MaxOwn>0</MaxOwn>
		<CanSell>不可出售</CanSell>
		<SellPrice>0</SellPrice>
		<CanUse>可以使用</CanUse>
		<CanUseBatch>0</CanUseBatch>
		<UseEffect>0</UseEffect>
		<UseEffectArgs>0</UseEffectArgs>
		<CompoundNumber>0</CompoundNumber>
		<CompoundHero>0</CompoundHero>
		<DayUseLimit>0</DayUseLimit>
	</Node>
	<Node>
		<Id>210401</Id>
		<Quality>绿</Quality>
		<BagLabel>道具</BagLabel>
		<MaxOwn>0</MaxOwn>
		<CanSell>不可出售</CanSell>
		<SellPrice>0</SellPrice>
		<CanUse>可以使用</CanUse>
		<CanUseBatch>0</CanUseBatch>
		<UseEffect>0</UseEffect>
		<UseEffectArgs>0</UseEffectArgs>
		<CompoundNumber>0</CompoundNumber>
		<CompoundHero>0</CompoundHero>
		<DayUseLimit>0</DayUseLimit>
	</Node>
	<Node>
		<Id>210402</Id>
		<Quality>蓝</Quality>
		<BagLabel>道具</BagLabel>
		<MaxOwn>0</MaxOwn>
		<CanSell>不可出售</CanSell>
		<SellPrice>0</SellPrice>
		<CanUse>可以使用</CanUse>
		<CanUseBatch>0</CanUseBatch>
		<UseEffect>0</UseEffect>
		<UseEffectArgs>0</UseEffectArgs>
		<CompoundNumber>0</CompoundNumber>
		<CompoundHero>0</CompoundHero>
		<DayUseLimit>0</DayUseLimit>
	</Node>
	<Node>
		<Id>210403</Id>
		<Quality>紫</Quality>
		<BagLabel>道具</BagLabel>
		<MaxOwn>0</MaxOwn>
		<CanSell>不可出售</CanSell>
		<SellPrice>0</SellPrice>
		<CanUse>可以使用</CanUse>
		<CanUseBatch>0</CanUseBatch>
		<UseEffect>0</UseEffect>
		<UseEffectArgs>0</UseEffectArgs>
		<CompoundNumber>0</CompoundNumber>
		<CompoundHero>0</CompoundHero>
		<DayUseLimit>0</DayUseLimit>
	</Node>
	<Node>
		<Id>210501</Id>
		<Quality>绿</Quality>
		<BagLabel>道具</BagLabel>
		<MaxOwn>0</MaxOwn>
		<CanSell>不可出售</CanSell>
		<SellPrice>0</SellPrice>
		<CanUse>可以使用</CanUse>
		<CanUseBatch>0</CanUseBatch>
		<UseEffect>0</UseEffect>
		<UseEffectArgs>0</UseEffectArgs>
		<CompoundNumber>0</CompoundNumber>
		<CompoundHero>0</CompoundHero>
		<DayUseLimit>0</DayUseLimit>
	</Node>
	<Node>
		<Id>210502</Id>
		<Quality>蓝</Quality>
		<BagLabel>道具</BagLabel>
		<MaxOwn>0</MaxOwn>
		<CanSell>不可出售</CanSell>
		<SellPrice>0</SellPrice>
		<CanUse>可以使用</CanUse>
		<CanUseBatch>0</CanUseBatch>
		<UseEffect>0</UseEffect>
		<UseEffectArgs>0</UseEffectArgs>
		<CompoundNumber>0</CompoundNumber>
		<CompoundHero>0</CompoundHero>
		<DayUseLimit>0</DayUseLimit>
	</Node>
	<Node>
		<Id>210503</Id>
		<Quality>紫</Quality>
		<BagLabel>道具</BagLabel>
		<MaxOwn>0</MaxOwn>
		<CanSell>不可出售</CanSell>
		<SellPrice>0</SellPrice>
		<CanUse>可以使用</CanUse>
		<CanUseBatch>0</CanUseBatch>
		<UseEffect>0</UseEffect>
		<UseEffectArgs>0</UseEffectArgs>
		<CompoundNumber>0</CompoundNumber>
		<CompoundHero>0</CompoundHero>
		<DayUseLimit>0</DayUseLimit>
	</Node>
	<Node>
		<Id>210601</Id>
		<Quality>紫</Quality>
		<BagLabel>道具</BagLabel>
		<MaxOwn>0</MaxOwn>
		<CanSell>不可出售</CanSell>
		<SellPrice>0</SellPrice>
		<CanUse>可以使用</CanUse>
		<CanUseBatch>0</CanUseBatch>
		<UseEffect>0</UseEffect>
		<UseEffectArgs>0</UseEffectArgs>
		<CompoundNumber>0</CompoundNumber>
		<CompoundHero>0</CompoundHero>
		<DayUseLimit>0</DayUseLimit>
	</Node>
	<Node>
		<Id>210602</Id>
		<Quality>橙</Quality>
		<BagLabel>道具</BagLabel>
		<MaxOwn>0</MaxOwn>
		<CanSell>不可出售</CanSell>
		<SellPrice>0</SellPrice>
		<CanUse>可以使用</CanUse>
		<CanUseBatch>0</CanUseBatch>
		<UseEffect>0</UseEffect>
		<UseEffectArgs>0</UseEffectArgs>
		<CompoundNumber>0</CompoundNumber>
		<CompoundHero>0</CompoundHero>
		<DayUseLimit>0</DayUseLimit>
	</Node>
	<Node>
		<Id>210603</Id>
		<Quality>金</Quality>
		<BagLabel>道具</BagLabel>
		<MaxOwn>0</MaxOwn>
		<CanSell>不可出售</CanSell>
		<SellPrice>0</SellPrice>
		<CanUse>可以使用</CanUse>
		<CanUseBatch>0</CanUseBatch>
		<UseEffect>0</UseEffect>
		<UseEffectArgs>0</UseEffectArgs>
		<CompoundNumber>0</CompoundNumber>
		<CompoundHero>0</CompoundHero>
		<DayUseLimit>0</DayUseLimit>
	</Node>
	<Node>
		<Id>210701</Id>
		<Quality>紫</Quality>
		<BagLabel>道具</BagLabel>
		<MaxOwn>0</MaxOwn>
		<CanSell>不可出售</CanSell>
		<SellPrice>0</SellPrice>
		<CanUse>可以使用</CanUse>
		<CanUseBatch>0</CanUseBatch>
		<UseEffect>0</UseEffect>
		<UseEffectArgs>0</UseEffectArgs>
		<CompoundNumber>0</CompoundNumber>
		<CompoundHero>0</CompoundHero>
		<DayUseLimit>0</DayUseLimit>
	</Node>
	<Node>
		<Id>210702</Id>
		<Quality>橙</Quality>
		<BagLabel>道具</BagLabel>
		<MaxOwn>0</MaxOwn>
		<CanSell>不可出售</CanSell>
		<SellPrice>0</SellPrice>
		<CanUse>可以使用</CanUse>
		<CanUseBatch>0</CanUseBatch>
		<UseEffect>0</UseEffect>
		<UseEffectArgs>0</UseEffectArgs>
		<CompoundNumber>0</CompoundNumber>
		<CompoundHero>0</CompoundHero>
		<DayUseLimit>0</DayUseLimit>
	</Node>
	<Node>
		<Id>210703</Id>
		<Quality>金</Quality>
		<BagLabel>道具</BagLabel>
		<MaxOwn>0</MaxOwn>
		<CanSell>不可出售</CanSell>
		<SellPrice>0</SellPrice>
		<CanUse>可以使用</CanUse>
		<CanUseBatch>0</CanUseBatch>
		<UseEffect>0</UseEffect>
		<UseEffectArgs>0</UseEffectArgs>
		<CompoundNumber>0</CompoundNumber>
		<CompoundHero>0</CompoundHero>
		<DayUseLimit>0</DayUseLimit>
	</Node>
	<Node>
		<Id>219901</Id>
		<Quality>橙</Quality>
		<BagLabel>道具</BagLabel>
		<MaxOwn>0</MaxOwn>
		<CanSell>不可出售</CanSell>
		<SellPrice>0</SellPrice>
		<CanUse>可以使用</CanUse>
		<CanUseBatch>0</CanUseBatch>
		<UseEffect>0</UseEffect>
		<UseEffectArgs>0</UseEffectArgs>
		<CompoundNumber>0</CompoundNumber>
		<CompoundHero>0</CompoundHero>
		<DayUseLimit>0</DayUseLimit>
	</Node>
	<Node>
		<Id>220101</Id>
		<Quality>紫</Quality>
		<BagLabel>资源</BagLabel>
		<MaxOwn>0</MaxOwn>
		<CanSell>不可出售</CanSell>
		<SellPrice>0</SellPrice>
		<CanUse>不可使用</CanUse>
		<CanUseBatch>0</CanUseBatch>
		<UseEffect>0</UseEffect>
		<UseEffectArgs>0</UseEffectArgs>
		<CompoundNumber>0</CompoundNumber>
		<CompoundHero>0</CompoundHero>
		<DayUseLimit>0</DayUseLimit>
	</Node>
	<Node>
		<Id>220102</Id>
		<Quality>橙</Quality>
		<BagLabel>资源</BagLabel>
		<MaxOwn>0</MaxOwn>
		<CanSell>不可出售</CanSell>
		<SellPrice>0</SellPrice>
		<CanUse>不可使用</CanUse>
		<CanUseBatch>0</CanUseBatch>
		<UseEffect>0</UseEffect>
		<UseEffectArgs>0</UseEffectArgs>
		<CompoundNumber>0</CompoundNumber>
		<CompoundHero>0</CompoundHero>
		<DayUseLimit>0</DayUseLimit>
	</Node>
	<Node>
		<Id>220103</Id>
		<Quality>金</Quality>
		<BagLabel>资源</BagLabel>
		<MaxOwn>0</MaxOwn>
		<CanSell>不可出售</CanSell>
		<SellPrice>0</SellPrice>
		<CanUse>不可使用</CanUse>
		<CanUseBatch>0</CanUseBatch>
		<UseEffect>0</UseEffect>
		<UseEffectArgs>0</UseEffectArgs>
		<CompoundNumber>0</CompoundNumber>
		<CompoundHero>0</CompoundHero>
		<DayUseLimit>0</DayUseLimit>
	</Node>
	<Node>
		<Id>220104</Id>
		<Quality>紫</Quality>
		<BagLabel>资源</BagLabel>
		<MaxOwn>0</MaxOwn>
		<CanSell>不可出售</CanSell>
		<SellPrice>0</SellPrice>
		<CanUse>不可使用</CanUse>
		<CanUseBatch>0</CanUseBatch>
		<UseEffect>0</UseEffect>
		<UseEffectArgs>0</UseEffectArgs>
		<CompoundNumber>0</CompoundNumber>
		<CompoundHero>0</CompoundHero>
		<DayUseLimit>0</DayUseLimit>
	</Node>
	<Node>
		<Id>220105</Id>
		<Quality>橙</Quality>
		<BagLabel>资源</BagLabel>
		<MaxOwn>0</MaxOwn>
		<CanSell>不可出售</CanSell>
		<SellPrice>0</SellPrice>
		<CanUse>不可使用</CanUse>
		<CanUseBatch>0</CanUseBatch>
		<UseEffect>0</UseEffect>
		<UseEffectArgs>0</UseEffectArgs>
		<CompoundNumber>0</CompoundNumber>
		<CompoundHero>0</CompoundHero>
		<DayUseLimit>0</DayUseLimit>
	</Node>
	<Node>
		<Id>220106</Id>
		<Quality>金</Quality>
		<BagLabel>资源</BagLabel>
		<MaxOwn>0</MaxOwn>
		<CanSell>不可出售</CanSell>
		<SellPrice>0</SellPrice>
		<CanUse>不可使用</CanUse>
		<CanUseBatch>0</CanUseBatch>
		<UseEffect>0</UseEffect>
		<UseEffectArgs>0</UseEffectArgs>
		<CompoundNumber>0</CompoundNumber>
		<CompoundHero>0</CompoundHero>
		<DayUseLimit>0</DayUseLimit>
	</Node>
	<Node>
		<Id>220107</Id>
		<Quality>紫</Quality>
		<BagLabel>资源</BagLabel>
		<MaxOwn>0</MaxOwn>
		<CanSell>不可出售</CanSell>
		<SellPrice>0</SellPrice>
		<CanUse>不可使用</CanUse>
		<CanUseBatch>0</CanUseBatch>
		<UseEffect>0</UseEffect>
		<UseEffectArgs>0</UseEffectArgs>
		<CompoundNumber>0</CompoundNumber>
		<CompoundHero>0</CompoundHero>
		<DayUseLimit>0</DayUseLimit>
	</Node>
	<Node>
		<Id>220108</Id>
		<Quality>橙</Quality>
		<BagLabel>资源</BagLabel>
		<MaxOwn>0</MaxOwn>
		<CanSell>不可出售</CanSell>
		<SellPrice>0</SellPrice>
		<CanUse>不可使用</CanUse>
		<CanUseBatch>0</CanUseBatch>
		<UseEffect>0</UseEffect>
		<UseEffectArgs>0</UseEffectArgs>
		<CompoundNumber>0</CompoundNumber>
		<CompoundHero>0</CompoundHero>
		<DayUseLimit>0</DayUseLimit>
	</Node>
	<Node>
		<Id>220109</Id>
		<Quality>金</Quality>
		<BagLabel>资源</BagLabel>
		<MaxOwn>0</MaxOwn>
		<CanSell>不可出售</CanSell>
		<SellPrice>0</SellPrice>
		<CanUse>不可使用</CanUse>
		<CanUseBatch>0</CanUseBatch>
		<UseEffect>0</UseEffect>
		<UseEffectArgs>0</UseEffectArgs>
		<CompoundNumber>0</CompoundNumber>
		<CompoundHero>0</CompoundHero>
		<DayUseLimit>0</DayUseLimit>
	</Node>
	<Node>
		<Id>220201</Id>
		<Quality>金</Quality>
		<BagLabel>资源</BagLabel>
		<MaxOwn>0</MaxOwn>
		<CanSell>不可出售</CanSell>
		<SellPrice>0</SellPrice>
		<CanUse>不可使用</CanUse>
		<CanUseBatch>0</CanUseBatch>
		<UseEffect>0</UseEffect>
		<UseEffectArgs>0</UseEffectArgs>
		<CompoundNumber>0</CompoundNumber>
		<CompoundHero>0</CompoundHero>
		<DayUseLimit>0</DayUseLimit>
	</Node>
	<Node>
		<Id>220202</Id>
		<Quality>金</Quality>
		<BagLabel>资源</BagLabel>
		<MaxOwn>0</MaxOwn>
		<CanSell>不可出售</CanSell>
		<SellPrice>0</SellPrice>
		<CanUse>不可使用</CanUse>
		<CanUseBatch>0</CanUseBatch>
		<UseEffect>0</UseEffect>
		<UseEffectArgs>0</UseEffectArgs>
		<CompoundNumber>0</CompoundNumber>
		<CompoundHero>0</CompoundHero>
		<DayUseLimit>0</DayUseLimit>
	</Node>
	<Node>
		<Id>220203</Id>
		<Quality>金</Quality>
		<BagLabel>资源</BagLabel>
		<MaxOwn>0</MaxOwn>
		<CanSell>不可出售</CanSell>
		<SellPrice>0</SellPrice>
		<CanUse>不可使用</CanUse>
		<CanUseBatch>0</CanUseBatch>
		<UseEffect>0</UseEffect>
		<UseEffectArgs>0</UseEffectArgs>
		<CompoundNumber>0</CompoundNumber>
		<CompoundHero>0</CompoundHero>
		<DayUseLimit>0</DayUseLimit>
	</Node>
	<Node>
		<Id>220204</Id>
		<Quality>金</Quality>
		<BagLabel>资源</BagLabel>
		<MaxOwn>0</MaxOwn>
		<CanSell>不可出售</CanSell>
		<SellPrice>0</SellPrice>
		<CanUse>不可使用</CanUse>
		<CanUseBatch>0</CanUseBatch>
		<UseEffect>0</UseEffect>
		<UseEffectArgs>0</UseEffectArgs>
		<CompoundNumber>0</CompoundNumber>
		<CompoundHero>0</CompoundHero>
		<DayUseLimit>0</DayUseLimit>
	</Node>
	<Node>
		<Id>220301</Id>
		<Quality>绿</Quality>
		<BagLabel>资源</BagLabel>
		<MaxOwn>0</MaxOwn>
		<CanSell>不可出售</CanSell>
		<SellPrice>0</SellPrice>
		<CanUse>不可使用</CanUse>
		<CanUseBatch>0</CanUseBatch>
		<UseEffect>0</UseEffect>
		<UseEffectArgs>0</UseEffectArgs>
		<CompoundNumber>0</CompoundNumber>
		<CompoundHero>0</CompoundHero>
		<DayUseLimit>0</DayUseLimit>
	</Node>
	<Node>
		<Id>220302</Id>
		<Quality>绿</Quality>
		<BagLabel>资源</BagLabel>
		<MaxOwn>0</MaxOwn>
		<CanSell>不可出售</CanSell>
		<SellPrice>0</SellPrice>
		<CanUse>不可使用</CanUse>
		<CanUseBatch>0</CanUseBatch>
		<UseEffect>0</UseEffect>
		<UseEffectArgs>0</UseEffectArgs>
		<CompoundNumber>0</CompoundNumber>
		<CompoundHero>0</CompoundHero>
		<DayUseLimit>0</DayUseLimit>
	</Node>
	<Node>
		<Id>220303</Id>
		<Quality>绿</Quality>
		<BagLabel>资源</BagLabel>
		<MaxOwn>0</MaxOwn>
		<CanSell>不可出售</CanSell>
		<SellPrice>0</SellPrice>
		<CanUse>不可使用</CanUse>
		<CanUseBatch>0</CanUseBatch>
		<UseEffect>0</UseEffect>
		<UseEffectArgs>0</UseEffectArgs>
		<CompoundNumber>0</CompoundNumber>
		<CompoundHero>0</CompoundHero>
		<DayUseLimit>0</DayUseLimit>
	</Node>
	<Node>
		<Id>220311</Id>
		<Quality>蓝</Quality>
		<BagLabel>资源</BagLabel>
		<MaxOwn>0</MaxOwn>
		<CanSell>不可出售</CanSell>
		<SellPrice>0</SellPrice>
		<CanUse>不可使用</CanUse>
		<CanUseBatch>0</CanUseBatch>
		<UseEffect>0</UseEffect>
		<UseEffectArgs>0</UseEffectArgs>
		<CompoundNumber>0</CompoundNumber>
		<CompoundHero>0</CompoundHero>
		<DayUseLimit>0</DayUseLimit>
	</Node>
	<Node>
		<Id>220312</Id>
		<Quality>蓝</Quality>
		<BagLabel>资源</BagLabel>
		<MaxOwn>0</MaxOwn>
		<CanSell>不可出售</CanSell>
		<SellPrice>0</SellPrice>
		<CanUse>不可使用</CanUse>
		<CanUseBatch>0</CanUseBatch>
		<UseEffect>0</UseEffect>
		<UseEffectArgs>0</UseEffectArgs>
		<CompoundNumber>0</CompoundNumber>
		<CompoundHero>0</CompoundHero>
		<DayUseLimit>0</DayUseLimit>
	</Node>
	<Node>
		<Id>220313</Id>
		<Quality>蓝</Quality>
		<BagLabel>资源</BagLabel>
		<MaxOwn>0</MaxOwn>
		<CanSell>不可出售</CanSell>
		<SellPrice>0</SellPrice>
		<CanUse>不可使用</CanUse>
		<CanUseBatch>0</CanUseBatch>
		<UseEffect>0</UseEffect>
		<UseEffectArgs>0</UseEffectArgs>
		<CompoundNumber>0</CompoundNumber>
		<CompoundHero>0</CompoundHero>
		<DayUseLimit>0</DayUseLimit>
	</Node>
	<Node>
		<Id>220321</Id>
		<Quality>紫</Quality>
		<BagLabel>资源</BagLabel>
		<MaxOwn>0</MaxOwn>
		<CanSell>不可出售</CanSell>
		<SellPrice>0</SellPrice>
		<CanUse>不可使用</CanUse>
		<CanUseBatch>0</CanUseBatch>
		<UseEffect>0</UseEffect>
		<UseEffectArgs>0</UseEffectArgs>
		<CompoundNumber>0</CompoundNumber>
		<CompoundHero>0</CompoundHero>
		<DayUseLimit>0</DayUseLimit>
	</Node>
	<Node>
		<Id>220322</Id>
		<Quality>紫</Quality>
		<BagLabel>资源</BagLabel>
		<MaxOwn>0</MaxOwn>
		<CanSell>不可出售</CanSell>
		<SellPrice>0</SellPrice>
		<CanUse>不可使用</CanUse>
		<CanUseBatch>0</CanUseBatch>
		<UseEffect>0</UseEffect>
		<UseEffectArgs>0</UseEffectArgs>
		<CompoundNumber>0</CompoundNumber>
		<CompoundHero>0</CompoundHero>
		<DayUseLimit>0</DayUseLimit>
	</Node>
	<Node>
		<Id>220323</Id>
		<Quality>紫</Quality>
		<BagLabel>资源</BagLabel>
		<MaxOwn>0</MaxOwn>
		<CanSell>不可出售</CanSell>
		<SellPrice>0</SellPrice>
		<CanUse>不可使用</CanUse>
		<CanUseBatch>0</CanUseBatch>
		<UseEffect>0</UseEffect>
		<UseEffectArgs>0</UseEffectArgs>
		<CompoundNumber>0</CompoundNumber>
		<CompoundHero>0</CompoundHero>
		<DayUseLimit>0</DayUseLimit>
	</Node>
	<Node>
		<Id>220331</Id>
		<Quality>橙</Quality>
		<BagLabel>资源</BagLabel>
		<MaxOwn>0</MaxOwn>
		<CanSell>不可出售</CanSell>
		<SellPrice>0</SellPrice>
		<CanUse>不可使用</CanUse>
		<CanUseBatch>0</CanUseBatch>
		<UseEffect>0</UseEffect>
		<UseEffectArgs>0</UseEffectArgs>
		<CompoundNumber>0</CompoundNumber>
		<CompoundHero>0</CompoundHero>
		<DayUseLimit>0</DayUseLimit>
	</Node>
	<Node>
		<Id>220332</Id>
		<Quality>橙</Quality>
		<BagLabel>资源</BagLabel>
		<MaxOwn>0</MaxOwn>
		<CanSell>不可出售</CanSell>
		<SellPrice>0</SellPrice>
		<CanUse>不可使用</CanUse>
		<CanUseBatch>0</CanUseBatch>
		<UseEffect>0</UseEffect>
		<UseEffectArgs>0</UseEffectArgs>
		<CompoundNumber>0</CompoundNumber>
		<CompoundHero>0</CompoundHero>
		<DayUseLimit>0</DayUseLimit>
	</Node>
	<Node>
		<Id>220333</Id>
		<Quality>橙</Quality>
		<BagLabel>资源</BagLabel>
		<MaxOwn>0</MaxOwn>
		<CanSell>不可出售</CanSell>
		<SellPrice>0</SellPrice>
		<CanUse>不可使用</CanUse>
		<CanUseBatch>0</CanUseBatch>
		<UseEffect>0</UseEffect>
		<UseEffectArgs>0</UseEffectArgs>
		<CompoundNumber>0</CompoundNumber>
		<CompoundHero>0</CompoundHero>
		<DayUseLimit>0</DayUseLimit>
	</Node>
	<Node>
		<Id>220341</Id>
		<Quality>金</Quality>
		<BagLabel>资源</BagLabel>
		<MaxOwn>0</MaxOwn>
		<CanSell>不可出售</CanSell>
		<SellPrice>0</SellPrice>
		<CanUse>不可使用</CanUse>
		<CanUseBatch>0</CanUseBatch>
		<UseEffect>0</UseEffect>
		<UseEffectArgs>0</UseEffectArgs>
		<CompoundNumber>0</CompoundNumber>
		<CompoundHero>0</CompoundHero>
		<DayUseLimit>0</DayUseLimit>
	</Node>
	<Node>
		<Id>220342</Id>
		<Quality>金</Quality>
		<BagLabel>资源</BagLabel>
		<MaxOwn>0</MaxOwn>
		<CanSell>不可出售</CanSell>
		<SellPrice>0</SellPrice>
		<CanUse>不可使用</CanUse>
		<CanUseBatch>0</CanUseBatch>
		<UseEffect>0</UseEffect>
		<UseEffectArgs>0</UseEffectArgs>
		<CompoundNumber>0</CompoundNumber>
		<CompoundHero>0</CompoundHero>
		<DayUseLimit>0</DayUseLimit>
	</Node>
	<Node>
		<Id>220343</Id>
		<Quality>金</Quality>
		<BagLabel>资源</BagLabel>
		<MaxOwn>0</MaxOwn>
		<CanSell>不可出售</CanSell>
		<SellPrice>0</SellPrice>
		<CanUse>不可使用</CanUse>
		<CanUseBatch>0</CanUseBatch>
		<UseEffect>0</UseEffect>
		<UseEffectArgs>0</UseEffectArgs>
		<CompoundNumber>0</CompoundNumber>
		<CompoundHero>0</CompoundHero>
		<DayUseLimit>0</DayUseLimit>
	</Node>
	<Node>
		<Id>231001</Id>
		<Quality>蓝</Quality>
		<BagLabel>碎片</BagLabel>
		<MaxOwn>0</MaxOwn>
		<CanSell>售为精华</CanSell>
		<SellPrice>5</SellPrice>
		<CanUse>可以合成</CanUse>
		<CanUseBatch>0</CanUseBatch>
		<UseEffect>0</UseEffect>
		<UseEffectArgs>0</UseEffectArgs>
		<CompoundNumber>10</CompoundNumber>
		<CompoundHero>101001</CompoundHero>
		<DayUseLimit>0</DayUseLimit>
	</Node>
	<Node>
		<Id>231002</Id>
		<Quality>蓝</Quality>
		<BagLabel>碎片</BagLabel>
		<MaxOwn>0</MaxOwn>
		<CanSell>售为精华</CanSell>
		<SellPrice>5</SellPrice>
		<CanUse>可以合成</CanUse>
		<CanUseBatch>0</CanUseBatch>
		<UseEffect>0</UseEffect>
		<UseEffectArgs>0</UseEffectArgs>
		<CompoundNumber>10</CompoundNumber>
		<CompoundHero>101002</CompoundHero>
		<DayUseLimit>0</DayUseLimit>
	</Node>
	<Node>
		<Id>231003</Id>
		<Quality>蓝</Quality>
		<BagLabel>碎片</BagLabel>
		<MaxOwn>0</MaxOwn>
		<CanSell>售为精华</CanSell>
		<SellPrice>5</SellPrice>
		<CanUse>可以合成</CanUse>
		<CanUseBatch>0</CanUseBatch>
		<UseEffect>0</UseEffect>
		<UseEffectArgs>0</UseEffectArgs>
		<CompoundNumber>10</CompoundNumber>
		<CompoundHero>101003</CompoundHero>
		<DayUseLimit>0</DayUseLimit>
	</Node>
	<Node>
		<Id>231004</Id>
		<Quality>蓝</Quality>
		<BagLabel>碎片</BagLabel>
		<MaxOwn>0</MaxOwn>
		<CanSell>售为精华</CanSell>
		<SellPrice>5</SellPrice>
		<CanUse>可以合成</CanUse>
		<CanUseBatch>0</CanUseBatch>
		<UseEffect>0</UseEffect>
		<UseEffectArgs>0</UseEffectArgs>
		<CompoundNumber>10</CompoundNumber>
		<CompoundHero>101004</CompoundHero>
		<DayUseLimit>0</DayUseLimit>
	</Node>
	<Node>
		<Id>231005</Id>
		<Quality>蓝</Quality>
		<BagLabel>碎片</BagLabel>
		<MaxOwn>0</MaxOwn>
		<CanSell>售为精华</CanSell>
		<SellPrice>5</SellPrice>
		<CanUse>可以合成</CanUse>
		<CanUseBatch>0</CanUseBatch>
		<UseEffect>0</UseEffect>
		<UseEffectArgs>0</UseEffectArgs>
		<CompoundNumber>10</CompoundNumber>
		<CompoundHero>101005</CompoundHero>
		<DayUseLimit>0</DayUseLimit>
	</Node>
	<Node>
		<Id>232001</Id>
		<Quality>紫</Quality>
		<BagLabel>碎片</BagLabel>
		<MaxOwn>0</MaxOwn>
		<CanSell>售为精华</CanSell>
		<SellPrice>10</SellPrice>
		<CanUse>可以合成</CanUse>
		<CanUseBatch>0</CanUseBatch>
		<UseEffect>0</UseEffect>
		<UseEffectArgs>0</UseEffectArgs>
		<CompoundNumber>20</CompoundNumber>
		<CompoundHero>102001</CompoundHero>
		<DayUseLimit>0</DayUseLimit>
	</Node>
	<Node>
		<Id>232002</Id>
		<Quality>紫</Quality>
		<BagLabel>碎片</BagLabel>
		<MaxOwn>0</MaxOwn>
		<CanSell>售为精华</CanSell>
		<SellPrice>10</SellPrice>
		<CanUse>可以合成</CanUse>
		<CanUseBatch>0</CanUseBatch>
		<UseEffect>0</UseEffect>
		<UseEffectArgs>0</UseEffectArgs>
		<CompoundNumber>20</CompoundNumber>
		<CompoundHero>102002</CompoundHero>
		<DayUseLimit>0</DayUseLimit>
	</Node>
	<Node>
		<Id>232003</Id>
		<Quality>紫</Quality>
		<BagLabel>碎片</BagLabel>
		<MaxOwn>0</MaxOwn>
		<CanSell>售为精华</CanSell>
		<SellPrice>10</SellPrice>
		<CanUse>可以合成</CanUse>
		<CanUseBatch>0</CanUseBatch>
		<UseEffect>0</UseEffect>
		<UseEffectArgs>0</UseEffectArgs>
		<CompoundNumber>20</CompoundNumber>
		<CompoundHero>102003</CompoundHero>
		<DayUseLimit>0</DayUseLimit>
	</Node>
	<Node>
		<Id>232004</Id>
		<Quality>紫</Quality>
		<BagLabel>碎片</BagLabel>
		<MaxOwn>0</MaxOwn>
		<CanSell>售为精华</CanSell>
		<SellPrice>10</SellPrice>
		<CanUse>可以合成</CanUse>
		<CanUseBatch>0</CanUseBatch>
		<UseEffect>0</UseEffect>
		<UseEffectArgs>0</UseEffectArgs>
		<CompoundNumber>20</CompoundNumber>
		<CompoundHero>102004</CompoundHero>
		<DayUseLimit>0</DayUseLimit>
	</Node>
	<Node>
		<Id>232005</Id>
		<Quality>紫</Quality>
		<BagLabel>碎片</BagLabel>
		<MaxOwn>0</MaxOwn>
		<CanSell>售为精华</CanSell>
		<SellPrice>10</SellPrice>
		<CanUse>可以合成</CanUse>
		<CanUseBatch>0</CanUseBatch>
		<UseEffect>0</UseEffect>
		<UseEffectArgs>0</UseEffectArgs>
		<CompoundNumber>20</CompoundNumber>
		<CompoundHero>102005</CompoundHero>
		<DayUseLimit>0</DayUseLimit>
	</Node>
	<Node>
		<Id>232006</Id>
		<Quality>紫</Quality>
		<BagLabel>碎片</BagLabel>
		<MaxOwn>0</MaxOwn>
		<CanSell>售为精华</CanSell>
		<SellPrice>10</SellPrice>
		<CanUse>可以合成</CanUse>
		<CanUseBatch>0</CanUseBatch>
		<UseEffect>0</UseEffect>
		<UseEffectArgs>0</UseEffectArgs>
		<CompoundNumber>20</CompoundNumber>
		<CompoundHero>102006</CompoundHero>
		<DayUseLimit>0</DayUseLimit>
	</Node>
	<Node>
		<Id>232007</Id>
		<Quality>紫</Quality>
		<BagLabel>碎片</BagLabel>
		<MaxOwn>0</MaxOwn>
		<CanSell>售为精华</CanSell>
		<SellPrice>10</SellPrice>
		<CanUse>可以合成</CanUse>
		<CanUseBatch>0</CanUseBatch>
		<UseEffect>0</UseEffect>
		<UseEffectArgs>0</UseEffectArgs>
		<CompoundNumber>20</CompoundNumber>
		<CompoundHero>102007</CompoundHero>
		<DayUseLimit>0</DayUseLimit>
	</Node>
	<Node>
		<Id>232008</Id>
		<Quality>紫</Quality>
		<BagLabel>碎片</BagLabel>
		<MaxOwn>0</MaxOwn>
		<CanSell>售为精华</CanSell>
		<SellPrice>10</SellPrice>
		<CanUse>可以合成</CanUse>
		<CanUseBatch>0</CanUseBatch>
		<UseEffect>0</UseEffect>
		<UseEffectArgs>0</UseEffectArgs>
		<CompoundNumber>20</CompoundNumber>
		<CompoundHero>102008</CompoundHero>
		<DayUseLimit>0</DayUseLimit>
	</Node>
	<Node>
		<Id>232009</Id>
		<Quality>紫</Quality>
		<BagLabel>碎片</BagLabel>
		<MaxOwn>0</MaxOwn>
		<CanSell>售为精华</CanSell>
		<SellPrice>10</SellPrice>
		<CanUse>可以合成</CanUse>
		<CanUseBatch>0</CanUseBatch>
		<UseEffect>0</UseEffect>
		<UseEffectArgs>0</UseEffectArgs>
		<CompoundNumber>20</CompoundNumber>
		<CompoundHero>102009</CompoundHero>
		<DayUseLimit>0</DayUseLimit>
	</Node>
	<Node>
		<Id>232010</Id>
		<Quality>紫</Quality>
		<BagLabel>碎片</BagLabel>
		<MaxOwn>0</MaxOwn>
		<CanSell>售为精华</CanSell>
		<SellPrice>10</SellPrice>
		<CanUse>可以合成</CanUse>
		<CanUseBatch>0</CanUseBatch>
		<UseEffect>0</UseEffect>
		<UseEffectArgs>0</UseEffectArgs>
		<CompoundNumber>20</CompoundNumber>
		<CompoundHero>102010</CompoundHero>
		<DayUseLimit>0</DayUseLimit>
	</Node>
	<Node>
		<Id>233001</Id>
		<Quality>橙</Quality>
		<BagLabel>碎片</BagLabel>
		<MaxOwn>0</MaxOwn>
		<CanSell>售为精华</CanSell>
		<SellPrice>20</SellPrice>
		<CanUse>可以合成</CanUse>
		<CanUseBatch>0</CanUseBatch>
		<UseEffect>0</UseEffect>
		<UseEffectArgs>0</UseEffectArgs>
		<CompoundNumber>50</CompoundNumber>
		<CompoundHero>103001</CompoundHero>
		<DayUseLimit>0</DayUseLimit>
	</Node>
	<Node>
		<Id>233002</Id>
		<Quality>橙</Quality>
		<BagLabel>碎片</BagLabel>
		<MaxOwn>0</MaxOwn>
		<CanSell>售为精华</CanSell>
		<SellPrice>20</SellPrice>
		<CanUse>可以合成</CanUse>
		<CanUseBatch>0</CanUseBatch>
		<UseEffect>0</UseEffect>
		<UseEffectArgs>0</UseEffectArgs>
		<CompoundNumber>50</CompoundNumber>
		<CompoundHero>103002</CompoundHero>
		<DayUseLimit>0</DayUseLimit>
	</Node>
	<Node>
		<Id>233003</Id>
		<Quality>橙</Quality>
		<BagLabel>碎片</BagLabel>
		<MaxOwn>0</MaxOwn>
		<CanSell>售为精华</CanSell>
		<SellPrice>20</SellPrice>
		<CanUse>可以合成</CanUse>
		<CanUseBatch>0</CanUseBatch>
		<UseEffect>0</UseEffect>
		<UseEffectArgs>0</UseEffectArgs>
		<CompoundNumber>50</CompoundNumber>
		<CompoundHero>103003</CompoundHero>
		<DayUseLimit>0</DayUseLimit>
	</Node>
	<Node>
		<Id>233004</Id>
		<Quality>橙</Quality>
		<BagLabel>碎片</BagLabel>
		<MaxOwn>0</MaxOwn>
		<CanSell>售为精华</CanSell>
		<SellPrice>20</SellPrice>
		<CanUse>可以合成</CanUse>
		<CanUseBatch>0</CanUseBatch>
		<UseEffect>0</UseEffect>
		<UseEffectArgs>0</UseEffectArgs>
		<CompoundNumber>50</CompoundNumber>
		<CompoundHero>103004</CompoundHero>
		<DayUseLimit>0</DayUseLimit>
	</Node>
	<Node>
		<Id>233005</Id>
		<Quality>橙</Quality>
		<BagLabel>碎片</BagLabel>
		<MaxOwn>0</MaxOwn>
		<CanSell>售为精华</CanSell>
		<SellPrice>20</SellPrice>
		<CanUse>可以合成</CanUse>
		<CanUseBatch>0</CanUseBatch>
		<UseEffect>0</UseEffect>
		<UseEffectArgs>0</UseEffectArgs>
		<CompoundNumber>50</CompoundNumber>
		<CompoundHero>103005</CompoundHero>
		<DayUseLimit>0</DayUseLimit>
	</Node>
	<Node>
		<Id>233006</Id>
		<Quality>橙</Quality>
		<BagLabel>碎片</BagLabel>
		<MaxOwn>0</MaxOwn>
		<CanSell>售为精华</CanSell>
		<SellPrice>20</SellPrice>
		<CanUse>可以合成</CanUse>
		<CanUseBatch>0</CanUseBatch>
		<UseEffect>0</UseEffect>
		<UseEffectArgs>0</UseEffectArgs>
		<CompoundNumber>50</CompoundNumber>
		<CompoundHero>103006</CompoundHero>
		<DayUseLimit>0</DayUseLimit>
	</Node>
	<Node>
		<Id>233007</Id>
		<Quality>橙</Quality>
		<BagLabel>碎片</BagLabel>
		<MaxOwn>0</MaxOwn>
		<CanSell>售为精华</CanSell>
		<SellPrice>20</SellPrice>
		<CanUse>可以合成</CanUse>
		<CanUseBatch>0</CanUseBatch>
		<UseEffect>0</UseEffect>
		<UseEffectArgs>0</UseEffectArgs>
		<CompoundNumber>50</CompoundNumber>
		<CompoundHero>103007</CompoundHero>
		<DayUseLimit>0</DayUseLimit>
	</Node>
	<Node>
		<Id>233008</Id>
		<Quality>橙</Quality>
		<BagLabel>碎片</BagLabel>
		<MaxOwn>0</MaxOwn>
		<CanSell>售为精华</CanSell>
		<SellPrice>20</SellPrice>
		<CanUse>可以合成</CanUse>
		<CanUseBatch>0</CanUseBatch>
		<UseEffect>0</UseEffect>
		<UseEffectArgs>0</UseEffectArgs>
		<CompoundNumber>50</CompoundNumber>
		<CompoundHero>103008</CompoundHero>
		<DayUseLimit>0</DayUseLimit>
	</Node>
	<Node>
		<Id>233009</Id>
		<Quality>橙</Quality>
		<BagLabel>碎片</BagLabel>
		<MaxOwn>0</MaxOwn>
		<CanSell>售为精华</CanSell>
		<SellPrice>20</SellPrice>
		<CanUse>可以合成</CanUse>
		<CanUseBatch>0</CanUseBatch>
		<UseEffect>0</UseEffect>
		<UseEffectArgs>0</UseEffectArgs>
		<CompoundNumber>50</CompoundNumber>
		<CompoundHero>103009</CompoundHero>
		<DayUseLimit>0</DayUseLimit>
	</Node>
	<Node>
		<Id>233010</Id>
		<Quality>橙</Quality>
		<BagLabel>碎片</BagLabel>
		<MaxOwn>0</MaxOwn>
		<CanSell>售为精华</CanSell>
		<SellPrice>20</SellPrice>
		<CanUse>可以合成</CanUse>
		<CanUseBatch>0</CanUseBatch>
		<UseEffect>0</UseEffect>
		<UseEffectArgs>0</UseEffectArgs>
		<CompoundNumber>50</CompoundNumber>
		<CompoundHero>103010</CompoundHero>
		<DayUseLimit>0</DayUseLimit>
	</Node>
	<Node>
		<Id>233011</Id>
		<Quality>橙</Quality>
		<BagLabel>碎片</BagLabel>
		<MaxOwn>0</MaxOwn>
		<CanSell>售为精华</CanSell>
		<SellPrice>20</SellPrice>
		<CanUse>可以合成</CanUse>
		<CanUseBatch>0</CanUseBatch>
		<UseEffect>0</UseEffect>
		<UseEffectArgs>0</UseEffectArgs>
		<CompoundNumber>50</CompoundNumber>
		<CompoundHero>103011</CompoundHero>
		<DayUseLimit>0</DayUseLimit>
	</Node>
	<Node>
		<Id>233012</Id>
		<Quality>橙</Quality>
		<BagLabel>碎片</BagLabel>
		<MaxOwn>0</MaxOwn>
		<CanSell>售为精华</CanSell>
		<SellPrice>20</SellPrice>
		<CanUse>可以合成</CanUse>
		<CanUseBatch>0</CanUseBatch>
		<UseEffect>0</UseEffect>
		<UseEffectArgs>0</UseEffectArgs>
		<CompoundNumber>50</CompoundNumber>
		<CompoundHero>103012</CompoundHero>
		<DayUseLimit>0</DayUseLimit>
	</Node>
	<Node>
		<Id>233013</Id>
		<Quality>橙</Quality>
		<BagLabel>碎片</BagLabel>
		<MaxOwn>0</MaxOwn>
		<CanSell>售为精华</CanSell>
		<SellPrice>20</SellPrice>
		<CanUse>可以合成</CanUse>
		<CanUseBatch>0</CanUseBatch>
		<UseEffect>0</UseEffect>
		<UseEffectArgs>0</UseEffectArgs>
		<CompoundNumber>50</CompoundNumber>
		<CompoundHero>103013</CompoundHero>
		<DayUseLimit>0</DayUseLimit>
	</Node>
	<Node>
		<Id>233014</Id>
		<Quality>橙</Quality>
		<BagLabel>碎片</BagLabel>
		<MaxOwn>0</MaxOwn>
		<CanSell>售为精华</CanSell>
		<SellPrice>20</SellPrice>
		<CanUse>可以合成</CanUse>
		<CanUseBatch>0</CanUseBatch>
		<UseEffect>0</UseEffect>
		<UseEffectArgs>0</UseEffectArgs>
		<CompoundNumber>50</CompoundNumber>
		<CompoundHero>103014</CompoundHero>
		<DayUseLimit>0</DayUseLimit>
	</Node>
	<Node>
		<Id>233015</Id>
		<Quality>橙</Quality>
		<BagLabel>碎片</BagLabel>
		<MaxOwn>0</MaxOwn>
		<CanSell>售为精华</CanSell>
		<SellPrice>20</SellPrice>
		<CanUse>可以合成</CanUse>
		<CanUseBatch>0</CanUseBatch>
		<UseEffect>0</UseEffect>
		<UseEffectArgs>0</UseEffectArgs>
		<CompoundNumber>50</CompoundNumber>
		<CompoundHero>103015</CompoundHero>
		<DayUseLimit>0</DayUseLimit>
	</Node>
	<Node>
		<Id>234001</Id>
		<Quality>金</Quality>
		<BagLabel>碎片</BagLabel>
		<MaxOwn>0</MaxOwn>
		<CanSell>售为精华</CanSell>
		<SellPrice>40</SellPrice>
		<CanUse>可以合成</CanUse>
		<CanUseBatch>0</CanUseBatch>
		<UseEffect>0</UseEffect>
		<UseEffectArgs>0</UseEffectArgs>
		<CompoundNumber>99</CompoundNumber>
		<CompoundHero>104001</CompoundHero>
		<DayUseLimit>0</DayUseLimit>
	</Node>
	<Node>
		<Id>234002</Id>
		<Quality>金</Quality>
		<BagLabel>碎片</BagLabel>
		<MaxOwn>0</MaxOwn>
		<CanSell>售为精华</CanSell>
		<SellPrice>40</SellPrice>
		<CanUse>可以合成</CanUse>
		<CanUseBatch>0</CanUseBatch>
		<UseEffect>0</UseEffect>
		<UseEffectArgs>0</UseEffectArgs>
		<CompoundNumber>99</CompoundNumber>
		<CompoundHero>104002</CompoundHero>
		<DayUseLimit>0</DayUseLimit>
	</Node>
	<Node>
		<Id>234003</Id>
		<Quality>金</Quality>
		<BagLabel>碎片</BagLabel>
		<MaxOwn>0</MaxOwn>
		<CanSell>售为精华</CanSell>
		<SellPrice>40</SellPrice>
		<CanUse>可以合成</CanUse>
		<CanUseBatch>0</CanUseBatch>
		<UseEffect>0</UseEffect>
		<UseEffectArgs>0</UseEffectArgs>
		<CompoundNumber>99</CompoundNumber>
		<CompoundHero>104003</CompoundHero>
		<DayUseLimit>0</DayUseLimit>
	</Node>
	<Node>
		<Id>234004</Id>
		<Quality>金</Quality>
		<BagLabel>碎片</BagLabel>
		<MaxOwn>0</MaxOwn>
		<CanSell>售为精华</CanSell>
		<SellPrice>40</SellPrice>
		<CanUse>可以合成</CanUse>
		<CanUseBatch>0</CanUseBatch>
		<UseEffect>0</UseEffect>
		<UseEffectArgs>0</UseEffectArgs>
		<CompoundNumber>99</CompoundNumber>
		<CompoundHero>104004</CompoundHero>
		<DayUseLimit>0</DayUseLimit>
	</Node>
	<Node>
		<Id>234005</Id>
		<Quality>金</Quality>
		<BagLabel>碎片</BagLabel>
		<MaxOwn>0</MaxOwn>
		<CanSell>售为精华</CanSell>
		<SellPrice>40</SellPrice>
		<CanUse>可以合成</CanUse>
		<CanUseBatch>0</CanUseBatch>
		<UseEffect>0</UseEffect>
		<UseEffectArgs>0</UseEffectArgs>
		<CompoundNumber>99</CompoundNumber>
		<CompoundHero>104005</CompoundHero>
		<DayUseLimit>0</DayUseLimit>
	</Node>
	<Node>
		<Id>234006</Id>
		<Quality>金</Quality>
		<BagLabel>碎片</BagLabel>
		<MaxOwn>0</MaxOwn>
		<CanSell>售为精华</CanSell>
		<SellPrice>40</SellPrice>
		<CanUse>可以合成</CanUse>
		<CanUseBatch>0</CanUseBatch>
		<UseEffect>0</UseEffect>
		<UseEffectArgs>0</UseEffectArgs>
		<CompoundNumber>99</CompoundNumber>
		<CompoundHero>104006</CompoundHero>
		<DayUseLimit>0</DayUseLimit>
	</Node>
	<Node>
		<Id>234007</Id>
		<Quality>金</Quality>
		<BagLabel>碎片</BagLabel>
		<MaxOwn>0</MaxOwn>
		<CanSell>售为精华</CanSell>
		<SellPrice>40</SellPrice>
		<CanUse>可以合成</CanUse>
		<CanUseBatch>0</CanUseBatch>
		<UseEffect>0</UseEffect>
		<UseEffectArgs>0</UseEffectArgs>
		<CompoundNumber>99</CompoundNumber>
		<CompoundHero>104007</CompoundHero>
		<DayUseLimit>0</DayUseLimit>
	</Node>
	<Node>
		<Id>234008</Id>
		<Quality>金</Quality>
		<BagLabel>碎片</BagLabel>
		<MaxOwn>0</MaxOwn>
		<CanSell>售为精华</CanSell>
		<SellPrice>40</SellPrice>
		<CanUse>可以合成</CanUse>
		<CanUseBatch>0</CanUseBatch>
		<UseEffect>0</UseEffect>
		<UseEffectArgs>0</UseEffectArgs>
		<CompoundNumber>99</CompoundNumber>
		<CompoundHero>104008</CompoundHero>
		<DayUseLimit>0</DayUseLimit>
	</Node>
	<Node>
		<Id>234009</Id>
		<Quality>金</Quality>
		<BagLabel>碎片</BagLabel>
		<MaxOwn>0</MaxOwn>
		<CanSell>售为精华</CanSell>
		<SellPrice>40</SellPrice>
		<CanUse>可以合成</CanUse>
		<CanUseBatch>0</CanUseBatch>
		<UseEffect>0</UseEffect>
		<UseEffectArgs>0</UseEffectArgs>
		<CompoundNumber>99</CompoundNumber>
		<CompoundHero>104009</CompoundHero>
		<DayUseLimit>0</DayUseLimit>
	</Node>
	<Node>
		<Id>234010</Id>
		<Quality>金</Quality>
		<BagLabel>碎片</BagLabel>
		<MaxOwn>0</MaxOwn>
		<CanSell>售为精华</CanSell>
		<SellPrice>40</SellPrice>
		<CanUse>可以合成</CanUse>
		<CanUseBatch>0</CanUseBatch>
		<UseEffect>0</UseEffect>
		<UseEffectArgs>0</UseEffectArgs>
		<CompoundNumber>99</CompoundNumber>
		<CompoundHero>104010</CompoundHero>
		<DayUseLimit>0</DayUseLimit>
	</Node>
	<Node>
		<Id>240101</Id>
		<Quality>紫</Quality>
		<BagLabel>特殊</BagLabel>
		<MaxOwn>0</MaxOwn>
		<CanSell>不可出售</CanSell>
		<SellPrice>0</SellPrice>
		<CanUse>不可使用</CanUse>
		<CanUseBatch>0</CanUseBatch>
		<UseEffect>0</UseEffect>
		<UseEffectArgs>0</UseEffectArgs>
		<CompoundNumber>0</CompoundNumber>
		<CompoundHero>0</CompoundHero>
		<DayUseLimit>0</DayUseLimit>
	</Node>
	<Node>
		<Id>240102</Id>
		<Quality>橙</Quality>
		<BagLabel>特殊</BagLabel>
		<MaxOwn>0</MaxOwn>
		<CanSell>不可出售</CanSell>
		<SellPrice>0</SellPrice>
		<CanUse>不可使用</CanUse>
		<CanUseBatch>0</CanUseBatch>
		<UseEffect>0</UseEffect>
		<UseEffectArgs>0</UseEffectArgs>
		<CompoundNumber>0</CompoundNumber>
		<CompoundHero>0</CompoundHero>
		<DayUseLimit>0</DayUseLimit>
	</Node>
	<Node>
		<Id>240103</Id>
		<Quality>金</Quality>
		<BagLabel>特殊</BagLabel>
		<MaxOwn>0</MaxOwn>
		<CanSell>不可出售</CanSell>
		<SellPrice>0</SellPrice>
		<CanUse>不可使用</CanUse>
		<CanUseBatch>0</CanUseBatch>
		<UseEffect>0</UseEffect>
		<UseEffectArgs>0</UseEffectArgs>
		<CompoundNumber>0</CompoundNumber>
		<CompoundHero>0</CompoundHero>
		<DayUseLimit>0</DayUseLimit>
	</Node>
	<Node>
		<Id>240104</Id>
		<Quality>橙</Quality>
		<BagLabel>特殊</BagLabel>
		<MaxOwn>0</MaxOwn>
		<CanSell>不可出售</CanSell>
		<SellPrice>0</SellPrice>
		<CanUse>不可使用</CanUse>
		<CanUseBatch>0</CanUseBatch>
		<UseEffect>0</UseEffect>
		<UseEffectArgs>0</UseEffectArgs>
		<CompoundNumber>0</CompoundNumber>
		<CompoundHero>0</CompoundHero>
		<DayUseLimit>0</DayUseLimit>
	</Node>
	<Node>
		<Id>240105</Id>
		<Quality>金</Quality>
		<BagLabel>特殊</BagLabel>
		<MaxOwn>0</MaxOwn>
		<CanSell>不可出售</CanSell>
		<SellPrice>0</SellPrice>
		<CanUse>不可使用</CanUse>
		<CanUseBatch>0</CanUseBatch>
		<UseEffect>0</UseEffect>
		<UseEffectArgs>0</UseEffectArgs>
		<CompoundNumber>0</CompoundNumber>
		<CompoundHero>0</CompoundHero>
		<DayUseLimit>0</DayUseLimit>
	</Node>
</Data>
